[
    {
       "Market":"BTCUSDT",
       "Pair":"B-BTC_USDT",
       "Total Quantity":"0.000325",
       "Remaining Quantity":"0.0",
       "Price Per Unit":"36835.58",
       "Avg Price":"36862.79",
       "Fee Amount":"0.01198040675",
       "Side":"sell",
       "Order Type":"limit_order",
       "Status":"filled",
       "Exchnage code":"B",
       "Created At":"2021-07-27 01: 40: 54 UTC",
       "Updated At":"2021-07-27 01: 40: 54 UTC"
    },
    {
       "Market":"ETHUSDT",
       "Pair":"B-ETH_USDT",
       "Total Quantity":"0.00955",
       "Remaining Quantity":"0.0",
       "Price Per Unit":"1754.0",
       "Avg Price":"1754.0",
       "Fee Amount":"0.0167507",
       "Side":"buy",
       "Order Type":"limit_order",
       "Status":"filled",
       "Exchnage code":"B",
       "Created At":"2021-06-22 00: 29: 27 UTC",
       "Updated At":"2021-06-22 13: 41: 09 UTC"
    },
    {
       "Market":"BTCUSDT",
       "Pair":"B-BTC_USDT",
       "Total Quantity":"0.001125",
       "Remaining Quantity":"0.0",
       "Price Per Unit":"30000.0",
       "Avg Price":"30000.0",
       "Fee Amount":"0.03375",
       "Side":"buy",
       "Order Type":"limit_order",
       "Status":"filled",
       "Exchnage code":"B",
       "Created At":"2021-06-21 15: 12: 57 UTC",
       "Updated At":"2021-06-22 12: 25: 34 UTC"
    },
    {
       "Market":"BTCUSDT",
       "Pair":"B-BTC_USDT",
       "Total Quantity":"0.00035",
       "Remaining Quantity":"0.0",
       "Price Per Unit":"31800.0",
       "Avg Price":"31800.0",
       "Fee Amount":"0.01113",
       "Side":"buy",
       "Order Type":"limit_order",
       "Status":"filled",
       "Exchnage code":"B",
       "Created At":"2021-06-21 23: 33: 54 UTC",
       "Updated At":"2021-06-21 23: 39: 57 UTC"
    },
    {
       "Market":"ADAUSDT",
       "Pair":"B-ADA_USDT",
       "Total Quantity":"14.05",
       "Remaining Quantity":"0.0",
       "Price Per Unit":"1.1924",
       "Avg Price":"1.1924",
       "Fee Amount":"0.01675322",
       "Side":"buy",
       "Order Type":"limit_order",
       "Status":"filled",
       "Exchnage code":"B",
       "Created At":"2021-06-21 23: 37: 18 UTC",
       "Updated At":"2021-06-21 23: 39: 09 UTC"
    },
    {
       "Market":"HBARUSDT",
       "Pair":"B-HBAR_USDT",
       "Total Quantity":"55.7",
       "Remaining Quantity":"0.0",
       "Price Per Unit":"0.1955",
       "Avg Price":"0.1955",
       "Fee Amount":"0.01088935",
       "Side":"sell",
       "Order Type":"limit_order",
       "Status":"filled",
       "Exchnage code":"B",
       "Created At":"2021-06-21 15: 03: 04 UTC",
       "Updated At":"2021-06-21 20: 07: 02 UTC"
    },
    {
       "Market":"BTCUSDT",
       "Pair":"B-BTC_USDT",
       "Total Quantity":"0.000685",
       "Remaining Quantity":"0.0",
       "Price Per Unit":"32829.0",
       "Avg Price":"32829.0",
       "Fee Amount":"0.022487865",
       "Side":"buy",
       "Order Type":"limit_order",
       "Status":"filled",
       "Exchnage code":"B",
       "Created At":"2021-06-21 15: 09: 59 UTC",
       "Updated At":"2021-06-21 15: 12: 21 UTC"
    },
    {
       "Market":"ADAUSDT",
       "Pair":"B-ADA_USDT",
       "Total Quantity":"9.19",
       "Remaining Quantity":"0.0",
       "Price Per Unit":"1.305",
       "Avg Price":"1.305",
       "Fee Amount":"0.01199295",
       "Side":"buy",
       "Order Type":"limit_order",
       "Status":"filled",
       "Exchnage code":"B",
       "Created At":"2021-06-21 14: 40: 47 UTC",
       "Updated At":"2021-06-21 15: 02: 10 UTC"
    },
    {
       "Market":"HBARUSDT",
       "Pair":"B-HBAR_USDT",
       "Total Quantity":"64.1",
       "Remaining Quantity":"0.0",
       "Price Per Unit":"0.1699",
       "Avg Price":"0.1699",
       "Fee Amount":"0.01089059",
       "Side":"buy",
       "Order Type":"limit_order",
       "Status":"filled",
       "Exchnage code":"B",
       "Created At":"2021-06-21 14: 55: 20 UTC",
       "Updated At":"2021-06-21 14: 57: 38 UTC"
    },
    {
       "Market":"ETHUSDT",
       "Pair":"B-ETH_USDT",
       "Total Quantity":"0.00599",
       "Remaining Quantity":"0.0",
       "Price Per Unit":"2002.0",
       "Avg Price":"2002.0",
       "Fee Amount":"0.01199198",
       "Side":"buy",
       "Order Type":"limit_order",
       "Status":"filled",
       "Exchnage code":"B",
       "Created At":"2021-06-21 14: 48: 18 UTC",
       "Updated At":"2021-06-21 14: 48: 32 UTC"
    },
    {
       "Market":"DOTINR",
       "Pair":"I-DOT_INR",
       "Total Quantity":"0.69",
       "Remaining Quantity":"0.0",
       "Price Per Unit":"1429.0",
       "Avg Price":"1429.0",
       "Fee Amount":"0.98601",
       "Side":"buy",
       "Order Type":"limit_order",
       "Status":"filled",
       "Exchnage code":"I",
       "Created At":"2021-06-10 21: 48: 26 UTC",
       "Updated At":"2021-06-21 06: 35: 48 UTC"
    },
    {
       "Market":"BTCUSDT",
       "Pair":"B-BTC_USDT",
       "Total Quantity":"0.000319",
       "Remaining Quantity":"0.0",
       "Price Per Unit":"34420.0",
       "Avg Price":"34420.0",
       "Fee Amount":"0.01097998",
       "Side":"buy",
       "Order Type":"limit_order",
       "Status":"filled",
       "Exchnage code":"B",
       "Created At":"2021-06-20 16: 07: 21 UTC",
       "Updated At":"2021-06-20 16: 07: 37 UTC"
    },
    {
       "Market":"ETHUSDT",
       "Pair":"B-ETH_USDT",
       "Total Quantity":"0.00544",
       "Remaining Quantity":"0.0",
       "Price Per Unit":"2202.0",
       "Avg Price":"2202.0",
       "Fee Amount":"0.01197888",
       "Side":"buy",
       "Order Type":"limit_order",
       "Status":"filled",
       "Exchnage code":"B",
       "Created At":"2021-06-19 03: 12: 42 UTC",
       "Updated At":"2021-06-19 03: 13: 56 UTC"
    },
    {
       "Market":"FILUSDT",
       "Pair":"B-FIL_USDT",
       "Total Quantity":"0.1767",
       "Remaining Quantity":"0.0",
       "Price Per Unit":"67.9",
       "Avg Price":"67.9",
       "Fee Amount":"0.01199793",
       "Side":"buy",
       "Order Type":"limit_order",
       "Status":"filled",
       "Exchnage code":"B",
       "Created At":"2021-06-18 04: 23: 16 UTC",
       "Updated At":"2021-06-18 05: 49: 19 UTC"
    },
    {
       "Market":"USDTINR",
       "Pair":"I-USDT_INR",
       "Total Quantity":"41.5",
       "Remaining Quantity":"0.0",
       "Price Per Unit":"76.64",
       "Avg Price":"76.64",
       "Fee Amount":"3.18056",
       "Side":"buy",
       "Order Type":"limit_order",
       "Status":"filled",
       "Exchnage code":"I",
       "Created At":"2021-06-18 04: 27: 11 UTC",
       "Updated At":"2021-06-18 04: 37: 14 UTC"
    },
    {
       "Market":"TRXINR",
       "Pair":"I-TRX_INR",
       "Total Quantity":"304.0",
       "Remaining Quantity":"0.0",
       "Price Per Unit":"5.48",
       "Avg Price":"5.48",
       "Fee Amount":"1.66592",
       "Side":"sell",
       "Order Type":"limit_order",
       "Status":"filled",
       "Exchnage code":"I",
       "Created At":"2021-06-17 11: 30: 47 UTC",
       "Updated At":"2021-06-17 11: 45: 34 UTC"
    },
    {
       "Market":"TRXINR",
       "Pair":"I-TRX_INR",
       "Total Quantity":"278.0",
       "Remaining Quantity":"0.0",
       "Price Per Unit":"5.47",
       "Avg Price":"5.47",
       "Fee Amount":"1.52066",
       "Side":"sell",
       "Order Type":"limit_order",
       "Status":"filled",
       "Exchnage code":"I",
       "Created At":"2021-06-17 11: 22: 47 UTC",
       "Updated At":"2021-06-17 11: 25: 12 UTC"
    },
    {
       "Market":"ETHUSDT",
       "Pair":"B-ETH_USDT",
       "Total Quantity":"0.00852",
       "Remaining Quantity":"0.0",
       "Price Per Unit":"2346.0",
       "Avg Price":"2346.0",
       "Fee Amount":"0.01998792",
       "Side":"buy",
       "Order Type":"limit_order",
       "Status":"filled",
       "Exchnage code":"B",
       "Created At":"2021-06-11 21: 58: 55 UTC",
       "Updated At":"2021-06-11 21: 59: 00 UTC"
    },
    {
       "Market":"ETHUSDT",
       "Pair":"B-ETH_USDT",
       "Total Quantity":"0.00511",
       "Remaining Quantity":"0.0",
       "Price Per Unit":"2346.0",
       "Avg Price":"2346.0",
       "Fee Amount":"0.01198806",
       "Side":"buy",
       "Order Type":"limit_order",
       "Status":"filled",
       "Exchnage code":"B",
       "Created At":"2021-06-11 21: 52: 54 UTC",
       "Updated At":"2021-06-11 21: 52: 57 UTC"
    },
    {
       "Market":"TRXINR",
       "Pair":"I-TRX_INR",
       "Total Quantity":"557.0",
       "Remaining Quantity":"0.0",
       "Price Per Unit":"5.38",
       "Avg Price":"5.38",
       "Fee Amount":"2.99666",
       "Side":"buy",
       "Order Type":"limit_order",
       "Status":"filled",
       "Exchnage code":"I",
       "Created At":"2021-06-09 01: 06: 21 UTC",
       "Updated At":"2021-06-11 16: 33: 55 UTC"
    },
    {
       "Market":"USDTINR",
       "Pair":"I-USDT_INR",
       "Total Quantity":"31.64",
       "Remaining Quantity":"0.0",
       "Price Per Unit":"76.46",
       "Avg Price":"76.46",
       "Fee Amount":"2.4191944",
       "Side":"buy",
       "Order Type":"limit_order",
       "Status":"filled",
       "Exchnage code":"I",
       "Created At":"2021-06-11 09: 51: 13 UTC",
       "Updated At":"2021-06-11 09: 59: 02 UTC"
    },
    {
       "Market":"USDTINR",
       "Pair":"I-USDT_INR",
       "Total Quantity":"27.3",
       "Remaining Quantity":"0.0",
       "Price Per Unit":"76.68",
       "Avg Price":"76.68",
       "Fee Amount":"2.093364",
       "Side":"buy",
       "Order Type":"limit_order",
       "Status":"filled",
       "Exchnage code":"I",
       "Created At":"2021-06-10 21: 29: 45 UTC",
       "Updated At":"2021-06-11 04: 09: 09 UTC"
    },
    {
       "Market":"ADAUSDT",
       "Pair":"B-ADA_USDT",
       "Total Quantity":"96.23",
       "Remaining Quantity":"0.0",
       "Price Per Unit":"1.5421",
       "Avg Price":"1.5422",
       "Fee Amount":"0.148405906",
       "Side":"buy",
       "Order Type":"market_order",
       "Status":"filled",
       "Exchnage code":"B",
       "Created At":"2021-06-10 21: 41: 58 UTC",
       "Updated At":"2021-06-10 21: 41: 58 UTC"
    },
    {
       "Market":"BNBUSDT",
       "Pair":"B-BNB_USDT",
       "Total Quantity":"0.1265",
       "Remaining Quantity":"0.0",
       "Price Per Unit":"350.0",
       "Avg Price":"350.0",
       "Fee Amount":"0.044275",
       "Side":"buy",
       "Order Type":"limit_order",
       "Status":"filled",
       "Exchnage code":"B",
       "Created At":"2021-06-10 11: 27: 24 UTC",
       "Updated At":"2021-06-10 17: 29: 41 UTC"
    },
    {
       "Market":"ETHUSDT",
       "Pair":"B-ETH_USDT",
       "Total Quantity":"0.02246",
       "Remaining Quantity":"0.0",
       "Price Per Unit":"2507.0",
       "Avg Price":"2507.0",
       "Fee Amount":"0.05630722",
       "Side":"buy",
       "Order Type":"limit_order",
       "Status":"filled",
       "Exchnage code":"B",
       "Created At":"2021-06-10 14: 30: 27 UTC",
       "Updated At":"2021-06-10 14: 48: 35 UTC"
    },
    {
       "Market":"FILUSDT",
       "Pair":"B-FIL_USDT",
       "Total Quantity":"0.1413",
       "Remaining Quantity":"0.0",
       "Price Per Unit":"75.06",
       "Avg Price":"75.06",
       "Fee Amount":"0.010605978",
       "Side":"buy",
       "Order Type":"limit_order",
       "Status":"filled",
       "Exchnage code":"B",
       "Created At":"2021-06-10 14: 39: 47 UTC",
       "Updated At":"2021-06-10 14: 45: 51 UTC"
    },
    {
       "Market":"ANKRUSDT",
       "Pair":"B-ANKR_USDT",
       "Total Quantity":"222.9",
       "Remaining Quantity":"0.0",
       "Price Per Unit":"0.0921",
       "Avg Price":"0.0921",
       "Fee Amount":"0.02052909",
       "Side":"sell",
       "Order Type":"stop_limit",
       "Status":"filled",
       "Exchnage code":"B",
       "Created At":"2021-06-09 15: 12: 04 UTC",
       "Updated At":"2021-06-09 19: 15: 56 UTC"
    },
    {
       "Market":"VETINR",
       "Pair":"I-VET_INR",
       "Total Quantity":"240.8",
       "Remaining Quantity":"0.0",
       "Price Per Unit":"8.96",
       "Avg Price":"8.96",
       "Fee Amount":"2.157568",
       "Side":"sell",
       "Order Type":"limit_order",
       "Status":"filled",
       "Exchnage code":"I",
       "Created At":"2021-06-09 15: 22: 11 UTC",
       "Updated At":"2021-06-09 16: 41: 05 UTC"
    },
    {
       "Market":"MATICINR",
       "Pair":"I-MATIC_INR",
       "Total Quantity":"18.0",
       "Remaining Quantity":"0.0",
       "Price Per Unit":"112.9",
       "Avg Price":"112.9",
       "Fee Amount":"2.0322",
       "Side":"sell",
       "Order Type":"limit_order",
       "Status":"filled",
       "Exchnage code":"I",
       "Created At":"2021-06-09 14: 16: 21 UTC",
       "Updated At":"2021-06-09 15: 17: 48 UTC"
    },
    {
       "Market":"TRXUSDT",
       "Pair":"B-TRX_USDT",
       "Total Quantity":"2162.5",
       "Remaining Quantity":"0.0",
       "Price Per Unit":"0.0",
       "Avg Price":"0.07326",
       "Fee Amount":"0.15842475",
       "Side":"sell",
       "Order Type":"market_order",
       "Status":"filled",
       "Exchnage code":"B",
       "Created At":"2021-06-09 15: 04: 37 UTC",
       "Updated At":"2021-06-09 15: 04: 37 UTC"
    },
    {
       "Market":"ANKRUSDT",
       "Pair":"B-ANKR_USDT",
       "Total Quantity":"222.9",
       "Remaining Quantity":"0.0",
       "Price Per Unit":"0.08972",
       "Avg Price":"0.08972",
       "Fee Amount":"0.019998588",
       "Side":"buy",
       "Order Type":"limit_order",
       "Status":"filled",
       "Exchnage code":"B",
       "Created At":"2021-06-09 10: 16: 05 UTC",
       "Updated At":"2021-06-09 14: 58: 45 UTC"
    },
    {
       "Market":"TRXUSDT",
       "Pair":"B-TRX_USDT",
       "Total Quantity":"2162.5",
       "Remaining Quantity":"0.0",
       "Price Per Unit":"0.0719",
       "Avg Price":"0.0719",
       "Fee Amount":"0.15548375",
       "Side":"buy",
       "Order Type":"limit_order",
       "Status":"filled",
       "Exchnage code":"B",
       "Created At":"2021-06-09 14: 57: 53 UTC",
       "Updated At":"2021-06-09 14: 58: 21 UTC"
    },
    {
       "Market":"ETHUSDT",
       "Pair":"B-ETH_USDT",
       "Total Quantity":"0.06692",
       "Remaining Quantity":"0.0",
       "Price Per Unit":"2514.0",
       "Avg Price":"2514.0",
       "Fee Amount":"0.16823688",
       "Side":"buy",
       "Order Type":"limit_order",
       "Status":"filled",
       "Exchnage code":"B",
       "Created At":"2021-06-09 14: 33: 59 UTC",
       "Updated At":"2021-06-09 14: 52: 56 UTC"
    },
    {
       "Market":"TRXUSDT",
       "Pair":"B-TRX_USDT",
       "Total Quantity":"2135.1",
       "Remaining Quantity":"0.0",
       "Price Per Unit":"0.0",
       "Avg Price":"0.07296",
       "Fee Amount":"0.155776896",
       "Side":"sell",
       "Order Type":"market_order",
       "Status":"filled",
       "Exchnage code":"B",
       "Created At":"2021-06-09 14: 50: 03 UTC",
       "Updated At":"2021-06-09 14: 50: 03 UTC"
    },
    {
       "Market":"TRXUSDT",
       "Pair":"B-TRX_USDT",
       "Total Quantity":"2135.1",
       "Remaining Quantity":"0.0",
       "Price Per Unit":"0.07265",
       "Avg Price":"0.07265",
       "Fee Amount":"0.155115015",
       "Side":"buy",
       "Order Type":"limit_order",
       "Status":"filled",
       "Exchnage code":"B",
       "Created At":"2021-06-09 14: 25: 40 UTC",
       "Updated At":"2021-06-09 14: 25: 54 UTC"
    },
    {
       "Market":"MITHUSDT",
       "Pair":"B-MITH_USDT",
       "Total Quantity":"458.4",
       "Remaining Quantity":"0.0",
       "Price Per Unit":"0.0643",
       "Avg Price":"0.0643",
       "Fee Amount":"0.02947512",
       "Side":"sell",
       "Order Type":"limit_order",
       "Status":"filled",
       "Exchnage code":"B",
       "Created At":"2021-06-09 12: 36: 37 UTC",
       "Updated At":"2021-06-09 14: 00: 52 UTC"
    },
    {
       "Market":"MATICINR",
       "Pair":"I-MATIC_INR",
       "Total Quantity":"18.0",
       "Remaining Quantity":"0.0",
       "Price Per Unit":"108.0",
       "Avg Price":"108.0",
       "Fee Amount":"1.944",
       "Side":"buy",
       "Order Type":"limit_order",
       "Status":"filled",
       "Exchnage code":"I",
       "Created At":"2021-06-09 00: 23: 25 UTC",
       "Updated At":"2021-06-09 01: 42: 58 UTC"
    },
    {
       "Market":"USDTINR",
       "Pair":"I-USDT_INR",
       "Total Quantity":"186.9",
       "Remaining Quantity":"0.0",
       "Price Per Unit":"77.29",
       "Avg Price":"77.28960353130016",
       "Fee Amount":"14.4454269",
       "Side":"buy",
       "Order Type":"limit_order",
       "Status":"filled",
       "Exchnage code":"I",
       "Created At":"2021-06-09 01: 15: 31 UTC",
       "Updated At":"2021-06-09 01: 16: 18 UTC"
    },
    {
       "Market":"ETHINR",
       "Pair":"I-ETH_INR",
       "Total Quantity":"0.0051",
       "Remaining Quantity":"0.0",
       "Price Per Unit":"194222.0",
       "Avg Price":"194088.56",
       "Fee Amount":"0.989851656",
       "Side":"buy",
       "Order Type":"limit_order",
       "Status":"filled",
       "Exchnage code":"I",
       "Created At":"2021-06-08 23: 55: 54 UTC",
       "Updated At":"2021-06-08 23: 55: 54 UTC"
    },
    {
       "Market":"USDTINR",
       "Pair":"I-USDT_INR",
       "Total Quantity":"300.0",
       "Remaining Quantity":"0.0",
       "Price Per Unit":"77.24",
       "Avg Price":"77.24",
       "Fee Amount":"23.172",
       "Side":"buy",
       "Order Type":"limit_order",
       "Status":"filled",
       "Exchnage code":"I",
       "Created At":"2021-06-08 19: 40: 26 UTC",
       "Updated At":"2021-06-08 20: 46: 28 UTC"
    },
    {
       "Market":"MATICINR",
       "Pair":"I-MATIC_INR",
       "Total Quantity":"1.0",
       "Remaining Quantity":"0.0",
       "Price Per Unit":"102.2",
       "Avg Price":"102.2",
       "Fee Amount":"0.1022",
       "Side":"sell",
       "Order Type":"limit_order",
       "Status":"filled",
       "Exchnage code":"I",
       "Created At":"2021-06-08 15: 44: 34 UTC",
       "Updated At":"2021-06-08 15: 45: 28 UTC"
    },
    {
       "Market":"MATICINR",
       "Pair":"I-MATIC_INR",
       "Total Quantity":"1.0",
       "Remaining Quantity":"0.0",
       "Price Per Unit":"100.0",
       "Avg Price":"100.0",
       "Fee Amount":"0.1",
       "Side":"buy",
       "Order Type":"limit_order",
       "Status":"filled",
       "Exchnage code":"I",
       "Created At":"2021-06-08 05: 16: 25 UTC",
       "Updated At":"2021-06-08 15: 19: 54 UTC"
    },
    {
       "Market":"ETHINR",
       "Pair":"I-ETH_INR",
       "Total Quantity":"0.0025",
       "Remaining Quantity":"0.0",
       "Price Per Unit":"197111.0",
       "Avg Price":"197111.0",
       "Fee Amount":"0.4927775",
       "Side":"buy",
       "Order Type":"limit_order",
       "Status":"filled",
       "Exchnage code":"I",
       "Created At":"2021-06-08 04: 32: 23 UTC",
       "Updated At":"2021-06-08 04: 33: 00 UTC"
    },
    {
       "Market":"EOSINR",
       "Pair":"I-EOS_INR",
       "Total Quantity":"1.2173",
       "Remaining Quantity":"0.0",
       "Price Per Unit":"392.67",
       "Avg Price":"391.6",
       "Fee Amount":"0.47669468",
       "Side":"buy",
       "Order Type":"limit_order",
       "Status":"filled",
       "Exchnage code":"I",
       "Created At":"2021-06-08 04: 20: 00 UTC",
       "Updated At":"2021-06-08 04: 20: 00 UTC"
    },
    {
       "Market":"ADAINR",
       "Pair":"I-ADA_INR",
       "Total Quantity":"15.0",
       "Remaining Quantity":"0.0",
       "Price Per Unit":"120.56",
       "Avg Price":"120.35",
       "Fee Amount":"1.80525",
       "Side":"buy",
       "Order Type":"limit_order",
       "Status":"filled",
       "Exchnage code":"I",
       "Created At":"2021-06-08 04: 07: 08 UTC",
       "Updated At":"2021-06-08 04: 07: 08 UTC"
    },
    {
       "Market":"VETINR",
       "Pair":"I-VET_INR",
       "Total Quantity":"117.9",
       "Remaining Quantity":"0.0",
       "Price Per Unit":"8.48",
       "Avg Price":"8.48",
       "Fee Amount":"0.999792",
       "Side":"buy",
       "Order Type":"limit_order",
       "Status":"filled",
       "Exchnage code":"I",
       "Created At":"2021-06-08 03: 21: 23 UTC",
       "Updated At":"2021-06-08 03: 21: 27 UTC"
    },
    {
       "Market":"USDTINR",
       "Pair":"I-USDT_INR",
       "Total Quantity":"48.52",
       "Remaining Quantity":"0.0",
       "Price Per Unit":"78.11",
       "Avg Price":"78.11",
       "Fee Amount":"3.7898972",
       "Side":"sell",
       "Order Type":"limit_order",
       "Status":"filled",
       "Exchnage code":"I",
       "Created At":"2021-06-08 01: 46: 09 UTC",
       "Updated At":"2021-06-08 01: 46: 09 UTC"
    },
    {
       "Market":"USDTINR",
       "Pair":"I-USDT_INR",
       "Total Quantity":"48.52",
       "Remaining Quantity":"0.0",
       "Price Per Unit":"78.12",
       "Avg Price":"78.12",
       "Fee Amount":"3.7903824",
       "Side":"buy",
       "Order Type":"limit_order",
       "Status":"filled",
       "Exchnage code":"I",
       "Created At":"2021-06-08 01: 19: 44 UTC",
       "Updated At":"2021-06-08 01: 19: 50 UTC"
    },
    {
       "Market":"USDTINR",
       "Pair":"I-USDT_INR",
       "Total Quantity":"49.04",
       "Remaining Quantity":"0.0",
       "Price Per Unit":"77.45",
       "Avg Price":"77.45",
       "Fee Amount":"3.798148",
       "Side":"sell",
       "Order Type":"limit_order",
       "Status":"filled",
       "Exchnage code":"I",
       "Created At":"2021-06-07 22: 41: 03 UTC",
       "Updated At":"2021-06-07 22: 41: 04 UTC"
    },
    {
       "Market":"MLNUSDT",
       "Pair":"H-MLN_USDT",
       "Total Quantity":"0.3308",
       "Remaining Quantity":"0.0",
       "Price Per Unit":"148.5",
       "Avg Price":"148.5",
       "Fee Amount":"0.0982476",
       "Side":"sell",
       "Order Type":"limit_order",
       "Status":"filled",
       "Exchnage code":"H",
       "Created At":"2021-06-07 21: 38: 44 UTC",
       "Updated At":"2021-06-07 21: 38: 45 UTC"
    },
    {
       "Market":"VETINR",
       "Pair":"I-VET_INR",
       "Total Quantity":"122.9",
       "Remaining Quantity":"0.0",
       "Price Per Unit":"9.73",
       "Avg Price":"9.73",
       "Fee Amount":"1.195817",
       "Side":"buy",
       "Order Type":"limit_order",
       "Status":"filled",
       "Exchnage code":"I",
       "Created At":"2021-06-07 20: 21: 30 UTC",
       "Updated At":"2021-06-07 20: 21: 31 UTC"
    },
    {
       "Market":"MLNUSDT",
       "Pair":"H-MLN_USDT",
       "Total Quantity":"0.3308",
       "Remaining Quantity":"0.0",
       "Price Per Unit":"174.6622",
       "Avg Price":"174.6228",
       "Fee Amount":"0.11553044448",
       "Side":"buy",
       "Order Type":"limit_order",
       "Status":"filled",
       "Exchnage code":"H",
       "Created At":"2021-06-07 10: 52: 45 UTC",
       "Updated At":"2021-06-07 10: 52: 46 UTC"
    },
    {
       "Market":"TKOUSDT",
       "Pair":"B-TKO_USDT",
       "Total Quantity":"12.04",
       "Remaining Quantity":"0.0",
       "Price Per Unit":"2.4234",
       "Avg Price":"2.4236",
       "Fee Amount":"0.029180144",
       "Side":"sell",
       "Order Type":"limit_order",
       "Status":"filled",
       "Exchnage code":"B",
       "Created At":"2021-06-07 10: 33: 44 UTC",
       "Updated At":"2021-06-07 10: 33: 45 UTC"
    },
    {
       "Market":"TKOUSDT",
       "Pair":"B-TKO_USDT",
       "Total Quantity":"12.04",
       "Remaining Quantity":"0.0",
       "Price Per Unit":"2.446",
       "Avg Price":"2.445",
       "Fee Amount":"0.0294378",
       "Side":"buy",
       "Order Type":"limit_order",
       "Status":"filled",
       "Exchnage code":"B",
       "Created At":"2021-06-07 10: 17: 57 UTC",
       "Updated At":"2021-06-07 10: 17: 58 UTC"
    },
    {
       "Market":"TKOUSDT",
       "Pair":"B-TKO_USDT",
       "Total Quantity":"12.2",
       "Remaining Quantity":"0.0",
       "Price Per Unit":"2.42",
       "Avg Price":"2.42",
       "Fee Amount":"0.029524",
       "Side":"sell",
       "Order Type":"limit_order",
       "Status":"filled",
       "Exchnage code":"B",
       "Created At":"2021-06-07 10: 10: 12 UTC",
       "Updated At":"2021-06-07 10: 10: 54 UTC"
    },
    {
       "Market":"MLNUSDT",
       "Pair":"H-MLN_USDT",
       "Total Quantity":"0.1624",
       "Remaining Quantity":"0.0",
       "Price Per Unit":"177.2",
       "Avg Price":"177.2",
       "Fee Amount":"0.05755456",
       "Side":"sell",
       "Order Type":"limit_order",
       "Status":"filled",
       "Exchnage code":"H",
       "Created At":"2021-06-07 08: 32: 53 UTC",
       "Updated At":"2021-06-07 08: 32: 54 UTC"
    },
    {
       "Market":"MLNUSDT",
       "Pair":"H-MLN_USDT",
       "Total Quantity":"0.1624",
       "Remaining Quantity":"0.0",
       "Price Per Unit":"177.8542",
       "Avg Price":"177.8542",
       "Fee Amount":"0.05776704416",
       "Side":"buy",
       "Order Type":"limit_order",
       "Status":"filled",
       "Exchnage code":"H",
       "Created At":"2021-06-07 08: 16: 13 UTC",
       "Updated At":"2021-06-07 08: 16: 13 UTC"
    },
    {
       "Market":"MLNUSDT",
       "Pair":"H-MLN_USDT",
       "Total Quantity":"0.1611",
       "Remaining Quantity":"0.0",
       "Price Per Unit":"180.0",
       "Avg Price":"180.0002",
       "Fee Amount":"0.05799606444",
       "Side":"sell",
       "Order Type":"limit_order",
       "Status":"filled",
       "Exchnage code":"H",
       "Created At":"2021-06-07 07: 52: 45 UTC",
       "Updated At":"2021-06-07 07: 52: 46 UTC"
    },
    {
       "Market":"MITHUSDT",
       "Pair":"B-MITH_USDT",
       "Total Quantity":"458.4",
       "Remaining Quantity":"0.0",
       "Price Per Unit":"0.05433",
       "Avg Price":"0.05433",
       "Fee Amount":"0.024904872",
       "Side":"buy",
       "Order Type":"limit_order",
       "Status":"filled",
       "Exchnage code":"B",
       "Created At":"2021-06-07 04: 26: 26 UTC",
       "Updated At":"2021-06-07 06: 09: 39 UTC"
    },
    {
       "Market":"TKOUSDT",
       "Pair":"B-TKO_USDT",
       "Total Quantity":"10.14",
       "Remaining Quantity":"0.0",
       "Price Per Unit":"2.46",
       "Avg Price":"2.46",
       "Fee Amount":"0.0249444",
       "Side":"sell",
       "Order Type":"limit_order",
       "Status":"filled",
       "Exchnage code":"B",
       "Created At":"2021-06-07 03: 45: 06 UTC",
       "Updated At":"2021-06-07 04: 05: 18 UTC"
    },
    {
       "Market":"TKOUSDT",
       "Pair":"B-TKO_USDT",
       "Total Quantity":"10.14",
       "Remaining Quantity":"0.0",
       "Price Per Unit":"2.46",
       "Avg Price":"2.46",
       "Fee Amount":"0.0249444",
       "Side":"buy",
       "Order Type":"limit_order",
       "Status":"filled",
       "Exchnage code":"B",
       "Created At":"2021-06-07 03: 17: 54 UTC",
       "Updated At":"2021-06-07 03: 18: 09 UTC"
    },
    {
       "Market":"USDTINR",
       "Pair":"I-USDT_INR",
       "Total Quantity":"24.98",
       "Remaining Quantity":"0.0",
       "Price Per Unit":"76.37",
       "Avg Price":"76.37",
       "Fee Amount":"1.9077226",
       "Side":"buy",
       "Order Type":"limit_order",
       "Status":"filled",
       "Exchnage code":"I",
       "Created At":"2021-06-07 03: 16: 47 UTC",
       "Updated At":"2021-06-07 03: 16: 47 UTC"
    },
    {
       "Market":"TKOUSDT",
       "Pair":"B-TKO_USDT",
       "Total Quantity":"12.2",
       "Remaining Quantity":"0.0",
       "Price Per Unit":"2.4975",
       "Avg Price":"2.4975",
       "Fee Amount":"0.0304695",
       "Side":"buy",
       "Order Type":"limit_order",
       "Status":"filled",
       "Exchnage code":"B",
       "Created At":"2021-06-07 02: 57: 40 UTC",
       "Updated At":"2021-06-07 02: 58: 38 UTC"
    },
    {
       "Market":"USDTINR",
       "Pair":"I-USDT_INR",
       "Total Quantity":"10.5",
       "Remaining Quantity":"0.0",
       "Price Per Unit":"76.53",
       "Avg Price":"76.53",
       "Fee Amount":"0.803565",
       "Side":"buy",
       "Order Type":"limit_order",
       "Status":"filled",
       "Exchnage code":"I",
       "Created At":"2021-06-07 02: 49: 45 UTC",
       "Updated At":"2021-06-07 02: 53: 42 UTC"
    },
    {
       "Market":"USDTINR",
       "Pair":"I-USDT_INR",
       "Total Quantity":"20.0",
       "Remaining Quantity":"0.0",
       "Price Per Unit":"77.1",
       "Avg Price":"77.1",
       "Fee Amount":"1.542",
       "Side":"buy",
       "Order Type":"limit_order",
       "Status":"filled",
       "Exchnage code":"I",
       "Created At":"2021-06-06 22: 23: 12 UTC",
       "Updated At":"2021-06-06 22: 23: 12 UTC"
    },
    {
       "Market":"MLNUSDT",
       "Pair":"H-MLN_USDT",
       "Total Quantity":"0.0708",
       "Remaining Quantity":"0.0",
       "Price Per Unit":"172.0",
       "Avg Price":"172.0",
       "Fee Amount":"0.0243552",
       "Side":"buy",
       "Order Type":"limit_order",
       "Status":"filled",
       "Exchnage code":"H",
       "Created At":"2021-06-06 20: 20: 50 UTC",
       "Updated At":"2021-06-06 20: 22: 08 UTC"
    },
    {
       "Market":"MLNUSDT",
       "Pair":"H-MLN_USDT",
       "Total Quantity":"0.0903",
       "Remaining Quantity":"0.0",
       "Price Per Unit":"177.0",
       "Avg Price":"177.0",
       "Fee Amount":"0.0319662",
       "Side":"buy",
       "Order Type":"limit_order",
       "Status":"filled",
       "Exchnage code":"H",
       "Created At":"2021-06-06 20: 00: 49 UTC",
       "Updated At":"2021-06-06 20: 01: 30 UTC"
    },
    {
       "Market":"BTCUSDT",
       "Pair":"B-BTC_USDT",
       "Total Quantity":"0.000777",
       "Remaining Quantity":"0.0",
       "Price Per Unit":"0.0",
       "Avg Price":"36255.76",
       "Fee Amount":"0.02817072552",
       "Side":"sell",
       "Order Type":"market_order",
       "Status":"filled",
       "Exchnage code":"B",
       "Created At":"2021-06-06 16: 44: 56 UTC",
       "Updated At":"2021-06-06 16: 44: 57 UTC"
    },
    {
       "Market":"ETHUSDT",
       "Pair":"B-ETH_USDT",
       "Total Quantity":"0.01069",
       "Remaining Quantity":"0.0",
       "Price Per Unit":"2625.46",
       "Avg Price":"2625.46",
       "Fee Amount":"0.0280661674",
       "Side":"buy",
       "Order Type":"limit_order",
       "Status":"filled",
       "Exchnage code":"B",
       "Created At":"2021-06-05 13: 51: 55 UTC",
       "Updated At":"2021-06-05 13: 55: 18 UTC"
    },
    {
       "Market":"BTCUSDT",
       "Pair":"B-BTC_USDT",
       "Total Quantity":"0.000777",
       "Remaining Quantity":"0.0",
       "Price Per Unit":"36127.0",
       "Avg Price":"36127.0",
       "Fee Amount":"0.028070679",
       "Side":"buy",
       "Order Type":"limit_order",
       "Status":"filled",
       "Exchnage code":"B",
       "Created At":"2021-06-05 10: 31: 45 UTC",
       "Updated At":"2021-06-05 11: 42: 07 UTC"
    },
    {
       "Market":"BTCUSDT",
       "Pair":"B-BTC_USDT",
       "Total Quantity":"0.00074",
       "Remaining Quantity":"0.0",
       "Price Per Unit":"0.0",
       "Avg Price":"37517.68",
       "Fee Amount":"0.0277630832",
       "Side":"sell",
       "Order Type":"market_order",
       "Status":"filled",
       "Exchnage code":"B",
       "Created At":"2021-06-05 03: 13: 12 UTC",
       "Updated At":"2021-06-05 03: 13: 13 UTC"
    },
    {
       "Market":"BTCUSDT",
       "Pair":"B-BTC_USDT",
       "Total Quantity":"0.00074",
       "Remaining Quantity":"0.0",
       "Price Per Unit":"37639.34",
       "Avg Price":"37669.02",
       "Fee Amount":"0.0278750748",
       "Side":"buy",
       "Order Type":"market_order",
       "Status":"filled",
       "Exchnage code":"B",
       "Created At":"2021-06-05 02: 56: 21 UTC",
       "Updated At":"2021-06-05 02: 56: 22 UTC"
    },
    {
       "Market":"ETHUSDT",
       "Pair":"B-ETH_USDT",
       "Total Quantity":"0.0071",
       "Remaining Quantity":"0.0",
       "Price Per Unit":"0.0",
       "Avg Price":"2748.44",
       "Fee Amount":"0.019513924",
       "Side":"sell",
       "Order Type":"market_order",
       "Status":"filled",
       "Exchnage code":"B",
       "Created At":"2021-06-05 02: 45: 47 UTC",
       "Updated At":"2021-06-05 02: 45: 47 UTC"
    },
    {
       "Market":"BTCUSDT",
       "Pair":"B-BTC_USDT",
       "Total Quantity":"0.00071",
       "Remaining Quantity":"0.0",
       "Price Per Unit":"0.0",
       "Avg Price":"37430.0",
       "Fee Amount":"0.0265753",
       "Side":"sell",
       "Order Type":"market_order",
       "Status":"filled",
       "Exchnage code":"B",
       "Created At":"2021-06-05 02: 40: 46 UTC",
       "Updated At":"2021-06-05 02: 40: 46 UTC"
    },
    {
       "Market":"DOGEUSDT",
       "Pair":"B-DOGE_USDT",
       "Total Quantity":"27.0",
       "Remaining Quantity":"0.0",
       "Price Per Unit":"0.0",
       "Avg Price":"0.38538",
       "Fee Amount":"0.01040526",
       "Side":"sell",
       "Order Type":"market_order",
       "Status":"filled",
       "Exchnage code":"B",
       "Created At":"2021-06-05 02: 29: 35 UTC",
       "Updated At":"2021-06-05 02: 29: 36 UTC"
    },
    {
       "Market":"BTCINR",
       "Pair":"I-BTC_INR",
       "Total Quantity":"0.00029",
       "Remaining Quantity":"0.0",
       "Price Per Unit":"2868000.0",
       "Avg Price":"2870000.0",
       "Fee Amount":"0.8323",
       "Side":"buy",
       "Order Type":"market_order",
       "Status":"filled",
       "Exchnage code":"I",
       "Created At":"2021-06-05 00: 31: 36 UTC",
       "Updated At":"2021-06-05 00: 31: 37 UTC"
    },
    {
       "Market":"TRXINR",
       "Pair":"I-TRX_INR",
       "Total Quantity":"25.0",
       "Remaining Quantity":"0.0",
       "Price Per Unit":"6.0",
       "Avg Price":"6.0",
       "Fee Amount":"0.15",
       "Side":"buy",
       "Order Type":"limit_order",
       "Status":"filled",
       "Exchnage code":"I",
       "Created At":"2021-06-05 00: 10: 45 UTC",
       "Updated At":"2021-06-05 00: 11: 15 UTC"
    },
    {
       "Market":"BTCINR",
       "Pair":"I-BTC_INR",
       "Total Quantity":"0.00042",
       "Remaining Quantity":"0.0",
       "Price Per Unit":"2822000.0",
       "Avg Price":"2827315.04",
       "Fee Amount":"1.1874723168",
       "Side":"buy",
       "Order Type":"market_order",
       "Status":"filled",
       "Exchnage code":"I",
       "Created At":"2021-06-05 00: 03: 51 UTC",
       "Updated At":"2021-06-05 00: 03: 51 UTC"
    },
    {
       "Market":"DOGEINR",
       "Pair":"I-DOGE_INR",
       "Total Quantity":"17.0",
       "Remaining Quantity":"0.0",
       "Price Per Unit":"28.8",
       "Avg Price":"28.8",
       "Fee Amount":"0.4896",
       "Side":"buy",
       "Order Type":"limit_order",
       "Status":"filled",
       "Exchnage code":"I",
       "Created At":"2021-06-04 23: 36: 58 UTC",
       "Updated At":"2021-06-05 00: 02: 08 UTC"
    },
    {
       "Market":"ETHINR",
       "Pair":"I-ETH_INR",
       "Total Quantity":"0.0071",
       "Remaining Quantity":"0.0",
       "Price Per Unit":"208811.99",
       "Avg Price":"208811.99",
       "Fee Amount":"1.482565129",
       "Side":"buy",
       "Order Type":"limit_order",
       "Status":"filled",
       "Exchnage code":"I",
       "Created At":"2021-06-04 22: 13: 39 UTC",
       "Updated At":"2021-06-04 22: 21: 05 UTC"
    },
    {
       "Market":"DOGEINR",
       "Pair":"I-DOGE_INR",
       "Total Quantity":"10.0",
       "Remaining Quantity":"0.0",
       "Price Per Unit":"29.8506",
       "Avg Price":"29.8506",
       "Fee Amount":"0.298506",
       "Side":"buy",
       "Order Type":"limit_order",
       "Status":"filled",
       "Exchnage code":"I",
       "Created At":"2021-06-04 20: 33: 21 UTC",
       "Updated At":"2021-06-04 20: 33: 21 UTC"
    }
 ]